mosa/.gitignore
mosa/__init__.py
mosa/mosa.py
mosa-0.8.5.dist-info/LICENSE
mosa-0.8.5.dist-info/METADATA
mosa-0.8.5.dist-info/WHEEL
mosa-0.8.5.dist-info/RECORD
