Metadata-Version: 2.1
Name: mosa
Version: 0.8.5
Summary: Multi-Objective Simulated Annealing (MOSA) implementation in pure Python.
License: GPL 3.0
Author: Roberto Gomes, PhD
Author-email: roberto.veiga@ufabc.edu.br
Requires-Python: >=3.10,<4.0
Classifier: License :: Other/Proprietary License
Classifier: Programming Language :: Python :: 3
Classifier: Programming Language :: Python :: 3.10
Classifier: Programming Language :: Python :: 3.11
Classifier: Programming Language :: Python :: 3.12
Requires-Dist: black[jupyter] (>=24.10.0,<25.0.0)
Requires-Dist: jupyter (>=1.0.0,<2.0.0)
Requires-Dist: matplotlib (>=3.8,<4.0)
Requires-Dist: numpy (>=1.25,<2.0)
Requires-Dist: scipy (>=1.12,<2.0)
